setup.py
gb_distributions/Binomialdistribution.py
gb_distributions/Gaussiandistribution.py
gb_distributions/Generaldistribution.py
gb_distributions/__init__.py
gb_distributions.egg-info/PKG-INFO
gb_distributions.egg-info/SOURCES.txt
gb_distributions.egg-info/dependency_links.txt
gb_distributions.egg-info/not-zip-safe
gb_distributions.egg-info/top_level.txt