Metadata-Version: 1.0
Name: gb-distributions
Version: 0.1
Summary: Gaussian & Binomial distributions
Home-page: UNKNOWN
Author: ['Chun-Yang Wei']
Author-email: UNKNOWN
License: UNKNOWN
Platform: UNKNOWN
